readmepp/ReadMe.py
readmepp/__init__.py
readmepp-0.0.3.dist-info/LICENSE
readmepp-0.0.3.dist-info/METADATA
readmepp-0.0.3.dist-info/WHEEL
readmepp-0.0.3.dist-info/top_level.txt
readmepp-0.0.3.dist-info/RECORD
