Metadata-Version: 2.1
Name: readmepp
Version: 0.0.3
Summary: BERT models for readability prediction in multiple languages
Home-page: https://github.com/tareknaous/readme
Author: Tarek Naous
Author-email: tareknaous@gmail.com
Project-URL: Bug Tracker, https://github.com/tareknaous/readme
Classifier: Programming Language :: Python :: 3
Classifier: License :: OSI Approved :: GNU General Public License v3 (GPLv3)
Classifier: Operating System :: OS Independent
Requires-Python: >=3.6
License-File: LICENSE
Requires-Dist: transformers >=4.35.2
